LICENSE
MANIFEST.in
README.rst
setup.cfg
setup.py
django_snoopy.egg-info/PKG-INFO
django_snoopy.egg-info/SOURCES.txt
django_snoopy.egg-info/dependency_links.txt
django_snoopy.egg-info/pbr.json
django_snoopy.egg-info/requires.txt
django_snoopy.egg-info/top_level.txt
snoopy/__init__.py
snoopy/core.py
snoopy/helpers.py
snoopy/middleware.py
snoopy/output.py
snoopy/query_tracker.py
snoopy/request.py