Metadata-Version: 1.1
Name: django-snoopy
Version: 0.0.2
Summary: Simple Request/SQL profiling for Django
Home-page: https://github.com/Pradeek/django-snoopy
Author: Pradeek
Author-email: jpradeek@gmail.com
License: MIT License
Platform: UNKNOWN
Classifier: Environment :: Web Environment
Classifier: Framework :: Django
Classifier: Intended Audience :: Developers
Classifier: Operating System :: OS Independent
Classifier: Programming Language :: Python
Classifier: Programming Language :: Python :: 2.7
Classifier: Programming Language :: Python :: 3.3
Classifier: Programming Language :: Python :: 3.4
Classifier: Topic :: Internet :: WWW/HTTP
Classifier: Topic :: Internet :: WWW/HTTP :: Dynamic Content
